raiutils/__init__.py
raiutils/exceptions.py
raiutils/version.py
raiutils/cohort/__init__.py
raiutils/cohort/cohort.py
raiutils/cohort/constants.py
raiutils/common/__init__.py
raiutils/common/retries.py
raiutils/data_processing/__init__.py
raiutils/data_processing/data_processing_utils.py
raiutils/dataset/__init__.py
raiutils/dataset/dataset.py
raiutils/models/__init__.py
raiutils/models/model_utils.py
raiutils/sampling/__init__.py
raiutils/sampling/random_sampling.py
raiutils/webservice/__init__.py
raiutils/webservice/webservice.py
raiutils-0.4.1.dist-info/LICENSE
raiutils-0.4.1.dist-info/METADATA
raiutils-0.4.1.dist-info/WHEEL
raiutils-0.4.1.dist-info/top_level.txt
raiutils-0.4.1.dist-info/RECORD
