Metadata-Version: 2.1
Name: raiutils
Version: 0.4.1
Summary: Common basic utilities used across various RAI tools
Home-page: https://github.com/microsoft/responsible-ai-widgets
Author: Roman Lutz, Ilya Matiach, Ke Xu
Author-email: raiwidgets-maintain@microsoft.com
Classifier: Programming Language :: Python :: 3.6
Classifier: Programming Language :: Python :: 3.7
Classifier: Programming Language :: Python :: 3.8
Classifier: Programming Language :: Python :: 3.9
Classifier: Programming Language :: Python :: 3.10
Classifier: License :: OSI Approved :: MIT License
Classifier: Operating System :: OS Independent
Classifier: Development Status :: 3 - Alpha
Requires-Python: >=3.6
License-File: LICENSE
Requires-Dist: numpy
Requires-Dist: pandas
Requires-Dist: requests
Requires-Dist: scikit-learn
Requires-Dist: scipy
